odoo/addons/l10n_pt_vat/README.rst
odoo/addons/l10n_pt_vat/__init__.py
odoo/addons/l10n_pt_vat/__manifest__.py
odoo/addons/l10n_pt_vat/data/vat_adjustment_norm.xml
odoo/addons/l10n_pt_vat/data/vat_exempt_reason.xml
odoo/addons/l10n_pt_vat/i18n/l10n_pt_vat.pot
odoo/addons/l10n_pt_vat/i18n/pt.po
odoo/addons/l10n_pt_vat/models/__init__.py
odoo/addons/l10n_pt_vat/models/account_journal.py
odoo/addons/l10n_pt_vat/models/account_move.py
odoo/addons/l10n_pt_vat/models/account_tax.py
odoo/addons/l10n_pt_vat/models/l10n_pt_vat_exempt_reason.py
odoo/addons/l10n_pt_vat/models/vat_adjustment_norm.py
odoo/addons/l10n_pt_vat/readme/CONFIGURATION.rst
odoo/addons/l10n_pt_vat/readme/CONTRIBUTORS.md
odoo/addons/l10n_pt_vat/readme/DESCRIPTION.md
odoo/addons/l10n_pt_vat/readme/USAGE.md
odoo/addons/l10n_pt_vat/security/ir.model.access.csv
odoo/addons/l10n_pt_vat/static/description/icon.png
odoo/addons/l10n_pt_vat/static/description/index.html
odoo/addons/l10n_pt_vat/tests/__init__.py
odoo/addons/l10n_pt_vat/tests/test_vat.py
odoo/addons/l10n_pt_vat/views/account_journal_view.xml
odoo/addons/l10n_pt_vat/views/account_move_view.xml
odoo/addons/l10n_pt_vat/views/account_tax_view.xml
odoo/addons/l10n_pt_vat/views/l10n_pt_vat_exempt_reason_view.xml
odoo/addons/l10n_pt_vat/views/vat_adjustment_norm_view.xml
odoo_addon_l10n_pt_vat-18.0.1.0.0.7.dist-info/METADATA
odoo_addon_l10n_pt_vat-18.0.1.0.0.7.dist-info/WHEEL
odoo_addon_l10n_pt_vat-18.0.1.0.0.7.dist-info/top_level.txt
odoo_addon_l10n_pt_vat-18.0.1.0.0.7.dist-info/RECORD
