Metadata-Version: 2.1
Name: odoo-addon-l10n_pt_vat
Version: 18.0.1.0.0.7
Requires-Python: >=3.10
Requires-Dist: odoo==18.0.*
Summary: Portuguese VAT requirements extensions
Home-page: https://github.com/OCA/l10n-portugal
License: AGPL-3
Author: Open Source Integrators, Sossia, Odoo Community Association (OCA)
Author-email: support@odoo-community.org
Classifier: Programming Language :: Python
Classifier: Framework :: Odoo
Classifier: Framework :: Odoo :: 18.0
Classifier: License :: OSI Approved :: GNU Affero General Public License v3
Classifier: Development Status :: 5 - Production/Stable
